{
  "kind": "collectionType",
  "collectionName": "posts",
  "info": {
    "singularName": "post",
    "pluralName": "posts",
    "displayName": "Post",
    "description": ""
  },
  "options": {
    "draftAndPublish": true
  },
  "pluginOptions": {},
  "attributes": {
    "postTitle": {
      "type": "string",
      "required": true
    },
    "postExcerpt": {
      "type": "text",
      "required": true
    },
    "featuredImage": {
      "type": "media",
      "multiple": false,
      "required": false,
      "allowedTypes": [
        "images"
      ]
    },
    "categories": {
      "type": "relation",
      "relation": "manyToMany",
      "target": "api::category.category",
      "mappedBy": "posts"
    },
    "comments": {
      "type": "relation",
      "relation": "oneToMany",
      "target": "api::comment.comment",
      "mappedBy": "post"
    },
    "user": {
      "type": "relation",
      "relation": "manyToOne",
      "target": "plugin::users-permissions.user",
      "inversedBy": "posts"
    },
    "post": {
      "type": "text"
    },
    "postContent": {
      "type": "text",
      "required": true
    }
  }
}
